client/__init__.py
client/client/__init__.py
client/client/add_contact.py
client/client/database.py
client/client/del_contact.py
client/client/main_window.py
client/client/main_window_conv.py
client/client/start_dialog.py
client/client/transport.py
client/common/__init__.py
client/common/decors.py
client/common/descripts.py
client/common/errors.py
client/common/metaclasses.py
client/common/utils.py
client/common/variables.py
client/log/__init__.py
client/log/client_log_config.py
client/log/server_log_config.py
client/tests/__init__.py
client/tests/test_client.py
client/tests/test_server.py
client/tests/test_utils.py
py_messenger_client_VM-0.2.0.dist-info/METADATA
py_messenger_client_VM-0.2.0.dist-info/WHEEL
py_messenger_client_VM-0.2.0.dist-info/top_level.txt
py_messenger_client_VM-0.2.0.dist-info/RECORD
